wazp/__init__.py
wazp/app.py
wazp/utils.py
wazp/callbacks/__init__.py
wazp/callbacks/dashboard.py
wazp/callbacks/home.py
wazp/callbacks/metadata.py
wazp/callbacks/roi.py
wazp/pages/01_metadata.py
wazp/pages/02_ROI.py
wazp/pages/03_pose_estimation.py
wazp/pages/04_dashboard.py
wazp/pages/home.py
WAZP-0.2.1.dist-info/LICENSE
WAZP-0.2.1.dist-info/METADATA
WAZP-0.2.1.dist-info/WHEEL
WAZP-0.2.1.dist-info/entry_points.txt
WAZP-0.2.1.dist-info/top_level.txt
WAZP-0.2.1.dist-info/RECORD
