Metadata-Version: 2.1
Name: WAZP
Version: 0.2.1
Summary: Wasp Animal-tracking Zoo project with Pose estimation
Author-email: Sofia Miñano <s.minano@ucl.ac.uk>, Nikoloz Sirmpilatze <niko.sirbiladze@gmail.com>, Sam Cunliffe <s.cunliffe@ucl.ac.uk>, Adam Tyson <code@adamltyson.com>
License: BSD-3-Clause
Project-URL: Homepage, https://github.com/SainsburyWellcomeCentre/WAZP
Project-URL: Bug tracker, https://github.com/SainsburyWellcomeCentre/WAZP/issues
Project-URL: Documentation, https://SainsburyWellcomeCentre.github.io/WAZP
Project-URL: Source code, https://github.com/SainsburyWellcomeCentre/WAZP
Project-URL: User support, https://github.com/SainsburyWellcomeCentre/WAZP/issues
Classifier: Development Status :: 2 - Pre-Alpha
Classifier: Programming Language :: Python
Classifier: Programming Language :: Python :: 3
Classifier: Programming Language :: Python :: 3.9
Classifier: Programming Language :: Python :: 3.10
Classifier: Operating System :: OS Independent
Classifier: License :: OSI Approved :: BSD License
Requires-Python: >=3.9.0
License-File: LICENSE
Requires-Dist: tables
Requires-Dist: blosc2
Requires-Dist: numpy
Requires-Dist: pillow
Requires-Dist: pandas
Requires-Dist: dash
Requires-Dist: dash-bootstrap-components
Requires-Dist: opencv-python
Requires-Dist: PyYAML
Requires-Dist: shapely
Requires-Dist: openpyxl
Requires-Dist: defusedxml
Provides-Extra: dev
Requires-Dist: pytest ; extra == 'dev'
Requires-Dist: pytest-cov ; extra == 'dev'
Requires-Dist: coverage ; extra == 'dev'
Requires-Dist: dash[testing] ; extra == 'dev'
Requires-Dist: tox ; extra == 'dev'
Requires-Dist: black ; extra == 'dev'
Requires-Dist: ruff ; extra == 'dev'
Requires-Dist: mypy ; extra == 'dev'
Requires-Dist: pre-commit ; extra == 'dev'
Requires-Dist: setuptools-scm ; extra == 'dev'
Requires-Dist: types-PyYAML ; extra == 'dev'
Requires-Dist: pandas-stubs ; extra == 'dev'
Requires-Dist: types-Pillow ; extra == 'dev'
